sphinx_rust-0.0.2.dist-info/METADATA
sphinx_rust-0.0.2.dist-info/WHEEL
sphinx_rust-0.0.2.dist-info/license_files/LICENSE
sphinx_rust/domain.py
sphinx_rust/py.typed
sphinx_rust/directives/struct.py
sphinx_rust/directives/_core.py
sphinx_rust/directives/module.py
sphinx_rust/directives/enum.py
sphinx_rust/directives/crate.py
sphinx_rust/directives/__init__.py
sphinx_rust/directives/function.py
sphinx_rust/config.py
sphinx_rust/cli/__init__.py
sphinx_rust/cli/__main__.py
sphinx_rust/__init__.py
sphinx_rust/sphinx_rust.pyi
sphinx_rust/sphinx_rust.cpython-39-x86_64-linux-gnu.so
sphinx_rust-0.0.2.dist-info/RECORD
